koncept/.ipynb_checkpoints/__init__-checkpoint.py
koncept/.ipynb_checkpoints/models-checkpoint.py
koncept/__init__.py
koncept/models.py
koncept-0.2.2.dist-info/LICENSE
koncept-0.2.2.dist-info/WHEEL
koncept-0.2.2.dist-info/METADATA
koncept-0.2.2.dist-info/RECORD
