Metadata-Version: 2.1
Name: koncept
Version: 0.2.2
Summary: Koncept IQA
Home-page: https://github.com/subpic/koncept
License: MIT
Keywords: Image Quality Assessment,Tensorflow,Keras,Deep learning IQA
Author: Vlad Hosu
Author-email: subpic@gmail.com
Maintainer: Vlad Hosu
Maintainer-email: subpic@gmail.com
Requires-Python: >=3.6.1,<4.0.0
Classifier: License :: OSI Approved :: MIT License
Classifier: Programming Language :: Python :: 3
Classifier: Programming Language :: Python :: 3.7
Classifier: Programming Language :: Python :: 3.8
Classifier: Programming Language :: Python :: 3.9
Requires-Dist: kuti (>=0.9.4,<0.10.0)
Project-URL: Repository, https://github.com/subpic/koncept
